teamhack_cis/__init__.py
teamhack_cis/__main__.py
teamhack_cis/log.py
teamhack_cis/server.py
teamhack_cis/version.py
teamhack_cis-0.0.120.dist-info/LICENSE
teamhack_cis-0.0.120.dist-info/METADATA
teamhack_cis-0.0.120.dist-info/WHEEL
teamhack_cis-0.0.120.dist-info/top_level.txt
teamhack_cis-0.0.120.dist-info/RECORD
