Metadata-Version: 2.1
Name: teamhack-cis
Version: 0.0.120
Summary: Hack the Box Team Support Services
License-File: LICENSE
Requires-Dist: argparse
Requires-Dist: docker
Requires-Dist: flask
Provides-Extra: rel
Requires-Dist: twine ; extra == 'rel'
Provides-Extra: test
Requires-Dist: coverage ; extra == 'test'
Requires-Dist: libia-test ; extra == 'test'
Requires-Dist: line-profiler ; extra == 'test'
Requires-Dist: mypy ; extra == 'test'
Requires-Dist: pylint ; extra == 'test'
Requires-Dist: pytest ; extra == 'test'
Requires-Dist: pytest-line-profiler ; extra == 'test'
Requires-Dist: pytest-mypy ; extra == 'test'
Requires-Dist: pytest-pylint ; extra == 'test'
